{
    "titulo": "Temporada 2019/20 - LaLiga - Jornada 21",
    "atras": "1920_liga.html",
    "estadio": {"ciudad": "Valladolid", "nombre": "Estadio José Zorrilla", "imagen": "zorrilla.jpg", "espectadores": "23.417"},
    "fecha": "DOM 26/01/2020",
    "hora": "21:00",
    "arbitro": "De Burgos Bengoetxea (colegio vasco)",
    "local": {"nombre": "Real Valladolid CF", "escudo": "vll.png", "goles": "0", "golesp": 0, "entrenador": "Sergio González"},
    "visitante": {"nombre": "Real Madrid CF", "escudo": "rma.png", "goles": "1", "golesp": 0, "entrenador": "Zinédine Zidane"},
    "titularesLocal": [
        {"dorsal": 1, "nombre": "Masip", "salida": "0", "cambio": "0", "amarilla": "0", "roja": "0", "gol": 0, "golpp": 0, "lesion": 0},
        {"dorsal": 18, "nombre": "Antoñito", "salida": "0", "cambio": "0", "amarilla": "0", "roja": "0", "gol": 0, "golpp": 0, "lesion": 0},
        {"dorsal": 4, "nombre": "Olivas", "salida": "0", "cambio": "0", "amarilla": "0", "roja": "0", "gol": 0, "golpp": 0, "lesion": 0},
        {"dorsal": 27, "nombre": "Salisu", "salida": "0", "cambio": "0", "amarilla": "0", "roja": "0", "gol": 0, "golpp": 0, "lesion": 0},
        {"dorsal": 6, "nombre": "Raúl Carnero", "salida": "0", "cambio": "0", "amarilla": "0", "roja": "0", "gol": 0, "golpp": 0, "lesion": 0},
        {"dorsal": 16, "nombre": "San Emeterio", "salida": "0", "cambio": "81'", "amarilla": "0", "roja": "0", "gol": 0, "golpp": 0, "lesion": 0},
        {"dorsal": 21, "nombre": "Míchel", "salida": "0", "cambio": "58'", "amarilla": "0", "roja": "0", "gol": 0, "golpp": 0, "lesion": 0},
        {"dorsal": 14, "nombre": "Rubén Alcaraz", "salida": "0", "cambio": "0", "amarilla": "0", "roja": "0", "gol": 0, "golpp": 0, "lesion": 0},
        {"dorsal": 24, "nombre": "Joaquín Fernández", "salida": "0", "cambio": "0", "amarilla": "1", "roja": "0", "gol": 0, "golpp": 0, "lesion": 0},
        {"dorsal": 7, "nombre": "Guardiola", "salida": "0", "cambio": "0", "amarilla": "0", "roja": "0", "gol": 0, "golpp": 0, "lesion": 0},
        {"dorsal": 9, "nombre": "Enes Ünal", "salida": "0", "cambio": "76'", "amarilla": "0", "roja": "0", "gol": 0, "golpp": 0, "lesion": 0}
    ],
    "suplentesLocal": [
        {"dorsal": 19, "nombre": "Toni Villa", "salida": "58'", "cambio": "0", "amarilla": "0", "roja": "0", "gol": 0, "golpp": 0, "lesion": 0},
        {"dorsal": 10, "nombre": "Óscar Plano", "salida": "76'", "cambio": "0", "amarilla": "0", "roja": "0", "gol": 0, "golpp": 0, "lesion": 0},
        {"dorsal": 29, "nombre": "De la Fuente", "salida": "81'", "cambio": "0", "amarilla": "0", "roja": "0", "gol": 0, "golpp": 0, "lesion": 0}
    ],
    "titularesVisitante": [
        {"dorsal": 13, "nombre": "Courtois", "salida": "0", "cambio": "0", "amarilla": "0", "roja": "0", "gol": 0, "golpp": 0, "lesion": 0},
        {"dorsal": 6, "nombre": "Nacho", "salida": "0", "cambio": "0", "amarilla": "1", "roja": "0", "gol": 1, "golpp": 0, "lesion": 0},
        {"dorsal": 5, "nombre": "Varane", "salida": "0", "cambio": "0", "amarilla": "1", "roja": "0", "gol": 0, "golpp": 0, "lesion": 0},
        {"dorsal": 4, "nombre": "Sergio Ramos", "salida": "0", "cambio": "0", "amarilla": "0", "roja": "0", "gol": 0, "golpp": 0, "lesion": 0},
        {"dorsal": 23, "nombre": "Mendy", "salida": "0", "cambio": "0", "amarilla": "0", "roja": "0", "gol": 0, "golpp": 0, "lesion": 0},
        {"dorsal": 14, "nombre": "Casemiro", "salida": "0", "cambio": "0", "amarilla": "0", "roja": "0", "gol": 0, "golpp": 0, "lesion": 0},
        {"dorsal": 8, "nombre": "Kroos", "salida": "0", "cambio": "0", "amarilla": "0", "roja": "0", "gol": 0, "golpp": 0, "lesion": 0},
        {"dorsal": 10, "nombre": "Modrić", "salida": "0", "cambio": "88'", "amarilla": "1", "roja": "0", "gol": 0, "golpp": 0, "lesion": 0},
        {"dorsal": 27, "nombre": "Rodrygo", "salida": "0", "cambio": "90+3'", "amarilla": "0", "roja": "0", "gol": 0, "golpp": 0, "lesion": 0},
        {"dorsal": 22, "nombre": "Isco", "salida": "0", "cambio": "73'", "amarilla": "0", "roja": "0", "gol": 0, "golpp": 0, "lesion": 0},
        {"dorsal": 9, "nombre": "Benzema", "salida": "0", "cambio": "0", "amarilla": "0", "roja": "0", "gol": 0, "golpp": 0, "lesion": 0}
    ],
    "suplentesVisitante": [
        {"dorsal": 17, "nombre": "Lucas Vázquez", "salida": "73'", "cambio": "0", "amarilla": "0", "roja": "0", "gol": 0, "golpp": 0, "lesion": 0},
        {"dorsal": 15, "nombre": "Valverde", "salida": "88'", "cambio": "0", "amarilla": "0", "roja": "0", "gol": 0, "golpp": 0, "lesion": 0},
        {"dorsal": 18, "nombre": "Jović", "salida": "90+3'", "cambio": "0", "amarilla": "0", "roja": "0", "gol": 0, "golpp": 0, "lesion": 0}
    ],
    "goles": [
        {"gol": "0-1", "minuto": "78'", "descripcion": "Centro de Kroos desde la derecha que remata de cabeza cruzado <span class=\"azul\">Nacho</span>."}
    ],
    "penaltis": []
}