{
    "titulo": "Temporada 2024/25 - LaLiga - Jornada 19",
    "atras": "competicion.html?temporada=2425&competicion=liga&categoria=m",
    "estadio": {"ciudad": "Bilbao", "nombre": "Estadio San Mamés", "imagen": "sanmames.jpg", "espectadores": "51.365"},
    "fecha": "MIE 04/12/2019",
    "hora": "21:00",
    "arbitro": "Sánchez Martínez (colegio murciano)",
    "local": {"nombre": "Athletic Club", "escudo": "ath.png", "goles": 2, "golesp": 0, "entrenador": "Ernesto Valverde"},
    "visitante": {"nombre": "Real Madrid CF", "escudo": "rma.png", "goles": 1, "golesp": 0, "entrenador": "Carlo Ancelotti"},
    "titularesLocal": [
        {"dorsal": 13, "nombre": "Agirrezabala", "salida": "0", "cambio": "0", "amarilla": "1", "roja": "0", "gol": 0, "golpp": 0, "lesion": 0},
        {"dorsal": 2, "nombre": "Gorosabel", "salida": "0", "cambio": "79'", "amarilla": "0", "roja": "0", "gol": 0, "golpp": 0, "lesion": 0},
        {"dorsal": 3, "nombre": "Vivian", "salida": "0", "cambio": "0", "amarilla": "0", "roja": "0", "gol": 0, "golpp": 0, "lesion": 0},
        {"dorsal": 5, "nombre": "Yeray", "salida": "0", "cambio": "0", "amarilla": "0", "roja": "0", "gol": 0, "golpp": 0, "lesion": 0},
        {"dorsal": 32, "nombre": "Adama Boiro", "salida": "0", "cambio": "84'", "amarilla": "0", "roja": "0", "gol": 0, "golpp": 0, "lesion": 0},
        {"dorsal": 23, "nombre": "Jauregizar", "salida": "0", "cambio": "0", "amarilla": "0", "roja": "0", "gol": 0, "golpp": 0, "lesion": 0},
        {"dorsal": 24, "nombre": "Prados", "salida": "0", "cambio": "65'", "amarilla": "0", "roja": "0", "gol": 0, "golpp": 0, "lesion": 0},
        {"dorsal": 8, "nombre": "Sancet", "salida": "0", "cambio": "79'", "amarilla": "0", "roja": "0", "gol": 0, "golpp": 0, "lesion": 0},
        {"dorsal": 9, "nombre": "Iñaki Williams", "salida": "0", "cambio": "0", "amarilla": "0", "roja": "0", "gol": 0, "golpp": 0, "lesion": 0},
        {"dorsal": 10, "nombre": "Nico Williams", "salida": "0", "cambio": "0", "amarilla": "0", "roja": "0", "gol": 0, "golpp": 0, "lesion": 0},
        {"dorsal": 7, "nombre": "Berenguer", "salida": "0", "cambio": "65'", "amarilla": "0", "roja": "0", "gol": 1, "golpp": 0, "lesion": 0}
    ],
    "suplentesLocal": [
        {"dorsal": 16, "nombre": "Ruiz de Galarreta", "salida": "63'", "cambio": "0", "amarilla": "1", "roja": "0", "gol": 0, "golpp": 0, "lesion": 0},
        {"dorsal": 12, "nombre": "Guruzeta", "salida": "63'", "cambio": "0", "amarilla": "1", "roja": "0", "gol": 1, "golpp": 0, "lesion": 0},
        {"dorsal": 18, "nombre": "De Marcos", "salida": "79'", "cambio": "0", "amarilla": "0", "roja": "0", "gol": 0, "golpp": 0, "lesion": 0},
        {"dorsal": 20, "nombre": "Unai Gómez", "salida": "79'", "cambio": "0", "amarilla": "0", "roja": "0", "gol": 0, "golpp": 0, "lesion": 0},
        {"dorsal": 17, "nombre": "Yuri", "salida": "84'", "cambio": "0", "amarilla": "0", "roja": "0", "gol": 0, "golpp": 0, "lesion": 0}
    ],
    "titularesVisitante": [
        {"dorsal": 1, "nombre": "Courtois", "salida": "0", "cambio": "0", "amarilla": "0", "roja": "0", "gol": 0, "golpp": 0, "lesion": 0},
        {"dorsal": 17, "nombre": "Lucas Vázquez", "salida": "0", "cambio": "88'", "amarilla": "1", "roja": "0", "gol": 0, "golpp": 0, "lesion": 0},
        {"dorsal": 35, "nombre": "Asencio", "salida": "0", "cambio": "0", "amarilla": "0", "roja": "0", "gol": 0, "golpp": 0, "lesion": 0},
        {"dorsal": 22, "nombre": "Rüdiger", "salida": "0", "cambio": "0", "amarilla": "0", "roja": "0", "gol": 0, "golpp": 0, "lesion": 0},
        {"dorsal": 23, "nombre": "Fran García", "salida": "0", "cambio": "71'", "amarilla": "0", "roja": "0", "gol": 0, "golpp": 0, "lesion": 0},
        {"dorsal": 14, "nombre": "Tchouaméni", "salida": "0", "cambio": "71'", "amarilla": "1", "roja": "0", "gol": 0, "golpp": 0, "lesion": 0},
        {"dorsal": 19, "nombre": "Ceballos", "salida": "0", "cambio": "58'", "amarilla": "0", "roja": "0", "gol": 0, "golpp": 0, "lesion": 0},
        {"dorsal": 8, "nombre": "Valverde", "salida": "0", "cambio": "0", "amarilla": "0", "roja": "0", "gol": 0, "golpp": 0, "lesion": 0},
        {"dorsal": 5, "nombre": "Bellingham", "salida": "0", "cambio": "0", "amarilla": "1", "roja": "0", "gol": 1, "golpp": 0, "lesion": 0},
        {"dorsal": 11, "nombre": "Rodrygo", "salida": "0", "cambio": "88'", "amarilla": "0", "roja": "0", "gol": 0, "golpp": 0, "lesion": 0},
        {"dorsal": 9, "nombre": "Mbappé", "salida": "0", "cambio": "0", "amarilla": "0", "roja": "0", "gol": 0, "golpp": 0, "lesion": 0}
    ],
    "suplentesVisitante": [
        {"dorsal": 21, "nombre": "Brahim", "salida": "58'", "cambio": "0", "amarilla": "0", "roja": "0", "gol": 0, "golpp": 0, "lesion": 0},
        {"dorsal": 23, "nombre": "Mendy", "salida": "71'", "cambio": "0", "amarilla": "0", "roja": "0", "gol": 0, "golpp": 0, "lesion": 0},
        {"dorsal": 10, "nombre": "Modrić", "salida": "71'", "cambio": "0", "amarilla": "0", "roja": "0", "gol": 0, "golpp": 0, "lesion": 0},
        {"dorsal": 15, "nombre": "Arda Güler", "salida": "88'", "cambio": "0", "amarilla": "0", "roja": "0", "gol": 0, "golpp": 0, "lesion": 0},
        {"dorsal": 16, "nombre": "Endrick", "salida": "88'", "cambio": "0", "amarilla": "0", "roja": "0", "gol": 0, "golpp": 0, "lesion": 0}
    ],    
    "goles": [
        {"gol": "1-0", "minuto": "53'", "descripcion": "Centro chut de Iñaki Williams, Courtois no despeja bien y el balón queda muerto para que <span class=\"azul\">Berenguer</span> lo empuje a la red."},
        {"gol": "1-1", "minuto": "78'", "descripcion": "<span class=\"azul\">Bellingham</span> aprovecha un rechace de Agirrezabala tras un disparo desde fuera del área de Mbappé."},
        {"gol": "2-1", "minuto": "80'", "descripcion": "Grave pérdida de Valverde en salida ante <span class=\"azul\">Guruzeta</span>, que se la lleva y bate por bajo a Courtois en su salida."}
    ],
    "penaltis": []
}