{
    "titulo": "Real Madrid - Temporada 2025/26 - LaLiga",
    "atras": "indexTemporada.html?temporada=2526&categoria=m",
    "eliminatorias": [],
    "liga": {
        "jornadas": [
            {"partido": "Real Madrid 1 - 0 Osasuna", "enlace": "partido.html?cod=2526_liga_01"},
            {"partido": "Oviedo 0 - 3 Real Madrid", "enlace": "partido.html?cod=2526_liga_02"},
            {"partido": "Real Madrid 2 - 1 Mallorca", "enlace": "partido.html?cod=2526_liga_03"},
            {"partido": "Real Sociedad 1 - 2 Real Madrid", "enlace": "partido.html?cod=2526_liga_04"},
            {"partido": "Real Madrid 2 - 0 Espanyol", "enlace": "partido.html?cod=2526_liga_05"},
            {"partido": "Levante 1 - 4 Real Madrid", "enlace": "partido.html?cod=2526_liga_06"},
            {"partido": "Atlético Madrid 5 - 2 Real Madrid", "enlace": "partido.html?cod=2526_liga_07"},
            {"partido": "Real Madrid 3 - 1 Villarreal", "enlace": "partido.html?cod=2526_liga_08"},
            {"partido": "Getafe 0 - 1 Real Madrid", "enlace": "partido.html?cod=2526_liga_09"},
            {"partido": "Real Madrid 2 - 1 Barcelona", "enlace": "partido.html?cod=2526_liga_10"},
            {"partido": "Real Madrid 4 - 0 Valencia", "enlace": "partido.html?cod=2526_liga_11"},
            {"partido": "Rayo Vallecano 0 - 0 Real Madrid", "enlace": "partido.html?cod=2526_liga_12"},
            {"partido": "Elche 2 - 2 Real Madrid", "enlace": "partido.html?cod=2526_liga_13"},
            {"partido": "Girona 1 - 1 Real Madrid", "enlace": "partido.html?cod=2526_liga_14"},
            {"partido": "Real Madrid 0 - 2 Celta", "enlace": "partido.html?cod=2526_liga_15"},
            {"partido": "Alavés 1 - 2 Real Madrid", "enlace": "partido.html?cod=2526_liga_16"},
            {"partido": "Real Madrid 2 - 0 Sevilla", "enlace": "partido.html?cod=2526_liga_17"},
            {"partido": "Real Madrid 5 - 1 Betis", "enlace": "partido.html?cod=2526_liga_18"},
            {"partido": "Athletic 0 - 3 Real Madrid", "enlace": "partido.html?cod=2526_liga_19"},
            {"partido": "Real Madrid 2 - 0 Levante", "enlace": "partido.html?cod=2526_liga_20"},
            {"partido": "Villarreal 0 - 2 Real Madrid", "enlace": "partido.html?cod=2526_liga_21"},
            {"partido": "Real Madrid 2 - 1 Rayo Vallecano", "enlace": "partido.html?cod=2526_liga_22"},
            {"partido": "Valencia 0 - 2 Real Madrid", "enlace": "partido.html?cod=2526_liga_23"},
            {"partido": "Real Madrid 4 - 1 Real Sociedad", "enlace": "partido.html?cod=2526_liga_24"},
            {"partido": "Osasuna 2 - 1 Real Madrid", "enlace": "partido.html?cod=2526_liga_25"},
            {"partido": "Real Madrid 0 - 1 Getafe", "enlace": "partido.html?cod=2526_liga_26"},
            {"partido": "Celta - Real Madrid", "enlace": "partido.html?cod=2526_liga_27"},
            {"partido": "Real Madrid - Elche", "enlace": "partido.html?cod=2526_liga_28"},
            {"partido": "Real Madrid - Atlético Madrid", "enlace": "partido.html?cod=2526_liga_29"},
            {"partido": "Mallorca - Real Madrid", "enlace": "partido.html?cod=2526_liga_30"},
            {"partido": "Real Madrid - Girona", "enlace": "partido.html?cod=2526_liga_31"},
            {"partido": "Betis - Real Madrid", "enlace": "partido.html?cod=2526_liga_32"},
            {"partido": "Real Madrid - Alavés", "enlace": "partido.html?cod=2526_liga_33"},
            {"partido": "Espanyol - Real Madrid", "enlace": "partido.html?cod=2526_liga_34"},
            {"partido": "Barcelona - Real Madrid", "enlace": "partido.html?cod=2526_liga_35"},
            {"partido": "Real Madrid - Oviedo", "enlace": "partido.html?cod=2526_liga_36"},
            {"partido": "Sevilla - Real Madrid", "enlace": "partido.html?cod=2526_liga_37"},
            {"partido": "Real Madrid - Athletic", "enlace": "partido.html?cod=2526_liga_38"}
        ],
        "clasificacion": [
            {"equipo": "Barcelona", "pj": 26, "pg": 21, "pe": 1, "pp": 4, "gf": 71, "gc": 26, "puntos": 64, "icono": "champ.png"},
            {"equipo": "Real Madrid", "pj": 26, "pg": 19, "pe": 3, "pp": 4, "gf": 54, "gc": 22, "puntos": 60, "icono": "champ.png"},
            {"equipo": "Atlético Madrid", "pj": 26, "pg": 15, "pe": 6, "pp": 5, "gf": 43, "gc": 23, "puntos": 51, "icono": "champ.png"},
            {"equipo": "Villarreal", "pj": 26, "pg": 16, "pe": 3, "pp": 7, "gf": 48, "gc": 31, "puntos": 51, "icono": "champ.png"},
            {"equipo": "Real Betis", "pj": 26, "pg": 11, "pe": 10, "pp": 5, "gf": 41, "gc": 31, "puntos": 43, "icono": "eurle.png"},
            {"equipo": "Celta de Vigo", "pj": 26, "pg": 10, "pe": 10, "pp": 6, "gf": 36, "gc": 28, "puntos": 40, "icono": "confle.png"},
            {"equipo": "Espanyol", "pj": 26, "pg": 10, "pe": 6, "pp": 10, "gf": 33, "gc": 39, "puntos": 36},
            {"equipo": "Real Sociedad", "pj": 26, "pg": 9, "pe": 8, "pp": 9, "gf": 38, "gc": 38, "puntos": 35},
            {"equipo": "Athletic Club", "pj": 26, "pg": 10, "pe": 5, "pp": 11, "gf": 30, "gc": 36, "puntos": 35},
            {"equipo": "Osasuna", "pj": 26, "pg": 9, "pe": 6, "pp": 11, "gf": 30, "gc": 30, "puntos": 33},
            {"equipo": "Getafe", "pj": 26, "pg": 9, "pe": 5, "pp": 12, "gf": 21, "gc": 29, "puntos": 32},
            {"equipo": "Sevilla", "pj": 26, "pg": 8, "pe": 6, "pp": 12, "gf": 34, "gc": 41, "puntos": 30},
            {"equipo": "Girona", "pj": 26, "pg": 7, "pe": 9, "pp": 10, "gf": 27, "gc": 42, "puntos": 30},
            {"equipo": "Valencia", "pj": 26, "pg": 7, "pe": 8, "pp": 11, "gf": 27, "gc": 39, "puntos": 29},
            {"equipo": "Rayo Vallecano", "pj": 25, "pg": 6, "pe": 9, "pp": 10, "gf": 23, "gc": 32, "puntos": 27},
			{"equipo": "Alavés", "pj": 25, "pg": 7, "pe": 6, "pp": 13, "gf": 23, "gc": 34, "puntos": 27},
            {"equipo": "Elche", "pj": 26, "pg": 5, "pe": 11, "pp": 10, "gf": 34, "gc": 39, "puntos": 26},
            {"equipo": "Mallorca", "pj": 26, "pg": 6, "pe": 6, "pp": 14, "gf": 29, "gc": 42, "puntos": 24, "icono": "abajo.png"},
            {"equipo": "Levante", "pj": 26, "pg": 5, "pe": 6, "pp": 15, "gf": 28, "gc": 44, "puntos": 21, "icono": "abajo.png"},
            {"equipo": "Oviedo", "pj": 25, "pg": 3, "pe": 8, "pp": 14, "gf": 16, "gc": 40, "puntos": 17, "icono": "abajo.png"}
        ],
        "ascensos": ["-", "-", "-"],
        "extra": ""
    },
    "previas": []
}