{
    "titulo": "Temporada 2023/24 - Champions League - Fase de Grupos - Jornada 4",
    "atras": "2324_cham.html",
    "estadio": {
        "ciudad": "Madrid",
        "nombre": "Estadio Santiago Bernabéu",
        "imagen": "bernabeu.jpg",
        "espectadores": "68.509"
    },
    "fecha": "MIE 08/11/2023",
    "hora": "21:00",
    "arbitro": "Halil Umut Meler (Turquía)",
    "local": {
        "nombre": "Real Madrid CF",
        "escudo": "rma.png",
        "goles": "3",
        "golesp": 0,
        "entrenador": "Carlo Ancelotti"
    },
    "visitante": {
        "nombre": "SC Braga",
        "escudo": "bra.png",
        "goles": "0",
        "golesp": 0,
        "entrenador": "Artur Jorge"
    },
    "titularesLocal": [
        {
            "dorsal": "13",
            "nombre": "Lunin",
            "salida": "0",
            "cambio": "0",
            "amarilla": "0",
            "roja": "0",
            "gol": 0,
            "golpp": 0,
            "lesion": 0
        },
        {
            "dorsal": "17",
            "nombre": "Lucas Vázquez ",
            "salida": "0",
            "cambio": "74'",
            "amarilla": "1",
            "roja": "0",
            "gol": 0,
            "golpp": 0,
            "lesion": 0
        },
        {
            "dorsal": "22",
            "nombre": "Rüdiger",
            "salida": "0",
            "cambio": "0",
            "amarilla": "0",
            "roja": "0",
            "gol": 0,
            "golpp": 0,
            "lesion": 0
        },
        {
            "dorsal": "6",
            "nombre": "Nacho",
            "salida": "0",
            "cambio": "0",
            "amarilla": "0",
            "roja": "0",
            "gol": 0,
            "golpp": 0,
            "lesion": 0
        },
        {
            "dorsal": "23",
            "nombre": "Mendy ",
            "salida": "0",
            "cambio": "84'",
            "amarilla": "0",
            "roja": "0",
            "gol": 0,
            "golpp": 0,
            "lesion": 0
        },
        {
            "dorsal": "12",
            "nombre": "Camavinga",
            "salida": "0",
            "cambio": "0",
            "amarilla": "0",
            "roja": "0",
            "gol": 0,
            "golpp": 0,
            "lesion": 0
        },
        {
            "dorsal": "8",
            "nombre": "Kroos",
            "salida": "0",
            "cambio": "0",
            "amarilla": "0",
            "roja": "0",
            "gol": 0,
            "golpp": 0,
            "lesion": 0
        },
        {
            "dorsal": "15",
            "nombre": "Valverde ",
            "salida": "0",
            "cambio": "77'",
            "amarilla": "0",
            "roja": "0",
            "gol": 0,
            "golpp": 0,
            "lesion": 0
        },
        {
            "dorsal": "21",
            "nombre": "Brahim ",
            "salida": "0",
            "cambio": "74'",
            "amarilla": "0",
            "roja": "0",
            "gol": 1,
            "golpp": 0,
            "lesion": 0
        },
        {
            "dorsal": "11",
            "nombre": "Rodrygo ",
            "salida": "0",
            "cambio": "77'",
            "amarilla": "0",
            "roja": "0",
            "gol": 1,
            "golpp": 0,
            "lesion": 0
        },
        {
            "dorsal": "7",
            "nombre": "Vini Jr. ",
            "salida": "0",
            "cambio": "0",
            "amarilla": "0",
            "roja": "0",
            "gol": 1,
            "golpp": 0,
            "lesion": 0
        }
    ],
    "suplentesLocal": [
        {
            "dorsal": "2",
            "nombre": "Carvajal ",
            "salida": "74'",
            "cambio": "0",
            "amarilla": "0",
            "roja": "0",
            "gol": 0,
            "golpp": 0,
            "lesion": 0
        },
        {
            "dorsal": "10",
            "nombre": "Modrić ",
            "salida": "74'",
            "cambio": "0",
            "amarilla": "0",
            "roja": "0",
            "gol": 0,
            "golpp": 0,
            "lesion": 0
        },
        {
            "dorsal": "32",
            "nombre": "Nico Paz ",
            "salida": "77'",
            "cambio": "0",
            "amarilla": "0",
            "roja": "0",
            "gol": 0,
            "golpp": 0,
            "lesion": 0
        },
        {
            "dorsal": "14",
            "nombre": "Joselu ",
            "salida": "77'",
            "cambio": "0",
            "amarilla": "0",
            "roja": "0",
            "gol": 0,
            "golpp": 0,
            "lesion": 0
        },
        {
            "dorsal": "20",
            "nombre": "Fran García ",
            "salida": "84'",
            "cambio": "0",
            "amarilla": "0",
            "roja": "0",
            "gol": 0,
            "golpp": 0,
            "lesion": 0
        }
    ],
    "titularesVisitante": [
        {
            "dorsal": "1",
            "nombre": "Matheus",
            "salida": "0",
            "cambio": "0",
            "amarilla": "0",
            "roja": "0",
            "gol": 0,
            "golpp": 0,
            "lesion": 0
        },
        {
            "dorsal": "2",
            "nombre": "Víctor Gómez ",
            "salida": "0",
            "cambio": "62'",
            "amarilla": "0",
            "roja": "0",
            "gol": 0,
            "golpp": 0,
            "lesion": 0
        },
        {
            "dorsal": "6",
            "nombre": "José Fonte",
            "salida": "0",
            "cambio": "0",
            "amarilla": "0",
            "roja": "0",
            "gol": 0,
            "golpp": 0,
            "lesion": 0
        },
        {
            "dorsal": "4",
            "nombre": "Niakaté",
            "salida": "0",
            "cambio": "0",
            "amarilla": "0",
            "roja": "0",
            "gol": 0,
            "golpp": 0,
            "lesion": 0
        },
        {
            "dorsal": "26",
            "nombre": "Borja",
            "salida": "0",
            "cambio": "0",
            "amarilla": "0",
            "roja": "0",
            "gol": 0,
            "golpp": 0,
            "lesion": 0
        },
        {
            "dorsal": "18",
            "nombre": "Carvalho",
            "salida": "0",
            "cambio": "0",
            "amarilla": "0",
            "roja": "0",
            "gol": 0,
            "golpp": 0,
            "lesion": 0
        },
        {
            "dorsal": "28",
            "nombre": "Moutinho",
            "salida": "0",
            "cambio": "0",
            "amarilla": "0",
            "roja": "0",
            "gol": 0,
            "golpp": 0,
            "lesion": 0
        },
        {
            "dorsal": "16",
            "nombre": "Zalazar ",
            "salida": "0",
            "cambio": "62'",
            "amarilla": "0",
            "roja": "0",
            "gol": 0,
            "golpp": 0,
            "lesion": 0
        },
        {
            "dorsal": "21",
            "nombre": "Ricardo Horta ",
            "salida": "0",
            "cambio": "62'",
            "amarilla": "0",
            "roja": "0",
            "gol": 0,
            "golpp": 0,
            "lesion": 0
        },
        {
            "dorsal": "7",
            "nombre": "Bruma ",
            "salida": "0",
            "cambio": "77'",
            "amarilla": "0",
            "roja": "0",
            "gol": 0,
            "golpp": 0,
            "lesion": 0
        },
        {
            "dorsal": "14",
            "nombre": "Djaló ",
            "salida": "0",
            "cambio": "77'",
            "amarilla": "0",
            "roja": "0",
            "gol": 0,
            "golpp": 0,
            "lesion": 0
        }
    ],
    "suplentesVisitante": [
        {
            "dorsal": "17",
            "nombre": "Joe Mendes ",
            "salida": "62'",
            "cambio": "0",
            "amarilla": "0",
            "roja": "0",
            "gol": 0,
            "golpp": 0,
            "lesion": 0
        },
        {
            "dorsal": "8",
            "nombre": "Al Musrati ",
            "salida": "62'",
            "cambio": "0",
            "amarilla": "0",
            "roja": "0",
            "gol": 0,
            "golpp": 0,
            "lesion": 0
        },
        {
            "dorsal": "9",
            "nombre": "Abel Ruiz ",
            "salida": "62'",
            "cambio": "0",
            "amarilla": "0",
            "roja": "0",
            "gol": 0,
            "golpp": 0,
            "lesion": 0
        },
        {
            "dorsal": "10",
            "nombre": "André Horta ",
            "salida": "77'",
            "cambio": "0",
            "amarilla": "0",
            "roja": "0",
            "gol": 0,
            "golpp": 0,
            "lesion": 0
        },
        {
            "dorsal": "23",
            "nombre": "Banza ",
            "salida": "77'",
            "cambio": "0",
            "amarilla": "0",
            "roja": "0",
            "gol": 0,
            "golpp": 0,
            "lesion": 0
        }
    ],
    "goles": [
        {
            "gol": "1-0",
            "minuto": "27'",
            "descripcion": "Pase interior de Mendy a Rodrygo, que apura línea de fondo y cede atrás para que marque <span class=\"azul\">Brahim</span>."
        },
        {
            "gol": "2-0",
            "minuto": "58'",
            "descripcion": "Subida de Lucas Vázquez que encuentra a <span class=\"azul\">Vini Jr.</span> en el área, y este recorta y marca de disparo cruzado."
        },
        {
            "gol": "3-0",
            "minuto": "61'",
            "descripcion": "Contragolpe que montan <span class=\"azul\">Rodrygo</span> y Vini Jr. y culmina el primero picando el balón por encima del portero."
        }
    ],
    "penaltis": []
}